scHiCPTR/__init__.py
scHiCPTR/args.py
scHiCPTR/dpt.py
scHiCPTR/embs.py
scHiCPTR/eva.py
scHiCPTR/ppca.py
scHiCPTR/prune.py
scHiCPTR/scHiCPTR.py
scHiCPTR/vis.py
scHiCPTR-0.1.2.dist-info/METADATA
scHiCPTR-0.1.2.dist-info/WHEEL
scHiCPTR-0.1.2.dist-info/top_level.txt
scHiCPTR-0.1.2.dist-info/RECORD
