Metadata-Version: 2.1
Name: scHiCPTR
Version: 0.1.2
Summary: An unsupervised pseudotime inference pipeline through dual graph refinement for single cell Hi-C data.
Home-page: https://github.com/lhqxinhun/scHiCPTR
Author: 
Author-email: 
License: UNKNOWN
Project-URL: Bug Tracker, https://github.com/lhqxinhun/scHiCPTR
Platform: UNKNOWN
Classifier: Programming Language :: Python :: 3
Classifier: License :: OSI Approved :: MIT License
Classifier: Operating System :: OS Independent
Requires-Python: >=3.6
Requires-Dist: numpy (==1.18.0)
Requires-Dist: tables (==3.6.1)
Requires-Dist: pandas
Requires-Dist: anndata (==0.7.4)
Requires-Dist: networkx (==2.5)
Requires-Dist: matplotlib (>=3.3.2)
Requires-Dist: seaborn
Requires-Dist: umap-learn (==0.5.1)
Requires-Dist: legacy-api-wrap
Requires-Dist: scanpy (==1.6.0)
Requires-Dist: multiprocess
Requires-Dist: igraph
Requires-Dist: python-louvain
Requires-Dist: munkres
Requires-Dist: louvain (==0.7.0)
Requires-Dist: fa2 (==0.3.5)
